harrix_pylib/__init__.py
harrix_pylib/funcs_dev.py
harrix_pylib/funcs_file.py
harrix_pylib/funcs_md.py
harrix_pylib/funcs_py.py
harrix_pylib/markdown_checker.py
harrix_pylib/python_checker.py
harrix_pylib-0.169.dist-info/METADATA
harrix_pylib-0.169.dist-info/WHEEL
harrix_pylib-0.169.dist-info/entry_points.txt
harrix_pylib-0.169.dist-info/licenses/LICENSE.md
harrix_pylib-0.169.dist-info/RECORD
