Metadata-Version: 2.4
Name: harrix-pylib
Version: 0.169
Summary: Common functions for working in Python
Author-email: Anton Sergienko <anton.b.sergienko@gmail.com>
License: # The MIT License
License-File: LICENSE.md
Requires-Python: >=3.10
Requires-Dist: libcst>=1.6.0
Requires-Dist: pypdf>=5.7.0
Requires-Dist: pyyaml>=6.0.2
Requires-Dist: requests>=2.32.3
Requires-Dist: ruff>=0.9.2
Requires-Dist: transliterate
